  
{
    "definitions": {},
    "$schema": "http://json-schema.org/draft-04/schema#",
    "type": "object",
    "title": "Change Password Schema",
    "required": [
      "user",
      "password",
      "funcao"
    ],
    "properties": {
      "user": {
        "type": "string",
        "title": "Username",
        "minLength": 3,
        "maxLength": 50
      },
      "password": {
        "title": "Password",
        "type": "string",
        "minLength": 1,
        "maxLength": 50
      },
      "funcao": {
        "title": "Funcao",
        "type": "string",
        "minLength": 1,
        "maxLength": 50
      }
    }
  }